{
  "compras_agiles": [
    {
      "codigo": "3413-60-COT26",
      "nombre": "ADQUISICIÓN DE VESTUARIO PARA LA SECCIÓN CONSTRUCCIÓN DEL CGVIDE",
      "organismo": "Ejercito de Chile",
      "region": "Región de Tarapacá  ",
      "monto": 560000,
      "fecha_cierre": "2026-06-25 14:30",
      "estado": "Publicada",
      "url": "https://www.mercadopublico.cl/BuscarLicitacion?txtBuscar=3413-60-COT26",
      "url_directa": "https://www.mercadopublico.cl/Procurement/Modules/RFB/DetailsAcquisition.aspx?qs=3413-60-COT26"
    },
    {
      "codigo": "792905-9-COT26",
      "nombre": "Mantención correctiva de frenos de vehículo",
      "organismo": "SUPERINTENDENCIA DE EDUCACION ESCOLAR",
      "region": "Región del Maule ",
      "monto": 600000,
      "fecha_cierre": "2026-06-26 11:59",
      "estado": "Publicada",
      "url": "https://www.mercadopublico.cl/BuscarLicitacion?txtBuscar=792905-9-COT26",
      "url_directa": "https://www.mercadopublico.cl/Procurement/Modules/RFB/DetailsAcquisition.aspx?qs=792905-9-COT26"
    },
    {
      "codigo": "1147293-97-COT26",
      "nombre": "Servicio de Mantención Preventiva y Diagnóstico Mecánico Integral de Vehículo Institucional  COQUIMBO LA SERENA",
      "organismo": "Fundación para la Innovación Agraria",
      "region": "Región de Coquimbo ",
      "monto": 350000,
      "fecha_cierre": "2026-06-24 15:00",
      "estado": "Publicada",
      "url": "https://www.mercadopublico.cl/BuscarLicitacion?txtBuscar=1147293-97-COT26",
      "url_directa": "https://www.mercadopublico.cl/Procurement/Modules/RFB/DetailsAcquisition.aspx?qs=1147293-97-COT26"
    },
    {
      "codigo": "4315-95-COT26",
      "nombre": "Limpieza y reparación de canaletas de los establecimientos: Escuela F-304 Elena Armijo Morales y Liceo C-20 Luis Correa Rojas",
      "organismo": "ILUSTRE MUNICIPALIDAD DE CUREPTO",
      "region": "Región del Maule ",
      "monto": 2500000,
      "fecha_cierre": "2026-06-30 17:30",
      "estado": "Publicada",
      "url": "https://www.mercadopublico.cl/BuscarLicitacion?txtBuscar=4315-95-COT26",
      "url_directa": "https://www.mercadopublico.cl/Procurement/Modules/RFB/DetailsAcquisition.aspx?qs=4315-95-COT26"
    },
    {
      "codigo": "3399-108-COT26",
      "nombre": "COTIZACIÓN DE MATERIALES ELÉCTRICOS PARA REPARACIÓN DE LA GUARDIA CUARTEL.",
      "organismo": "Ejercito de Chile",
      "region": "Región del Maule ",
      "monto": 110301,
      "fecha_cierre": "2026-06-24 14:00",
      "estado": "Publicada",
      "url": "https://www.mercadopublico.cl/BuscarLicitacion?txtBuscar=3399-108-COT26",
      "url_directa": "https://www.mercadopublico.cl/Procurement/Modules/RFB/DetailsAcquisition.aspx?qs=3399-108-COT26"
    },
    {
      "codigo": "1057439-3815-COT26",
      "nombre": "Reparación para ventilador mecánico SLE 5000",
      "organismo": "SERVICIO DE SALUD COQUIMBO HOSPITAL LA SERENA",
      "region": "Región de Coquimbo ",
      "monto": 1654100,
      "fecha_cierre": "2026-06-29 11:00",
      "estado": "Publicada",
      "url": "https://www.mercadopublico.cl/BuscarLicitacion?txtBuscar=1057439-3815-COT26",
      "url_directa": "https://www.mercadopublico.cl/Procurement/Modules/RFB/DetailsAcquisition.aspx?qs=1057439-3815-COT26"
    },
    {
      "codigo": "2927-183-COT26",
      "nombre": "CONTRATACION DE PROFESIONAL DEL AREA DE LA CONSTRUCCION PARA DICTAR IMPARTIR TALLER",
      "organismo": "I MUNICIPALIDAD DE QUELLON",
      "region": "Región de los Lagos ",
      "monto": 450000,
      "fecha_cierre": "2026-06-26 14:00",
      "estado": "Publicada",
      "url": "https://www.mercadopublico.cl/BuscarLicitacion?txtBuscar=2927-183-COT26",
      "url_directa": "https://www.mercadopublico.cl/Procurement/Modules/RFB/DetailsAcquisition.aspx?qs=2927-183-COT26"
    },
    {
      "codigo": "1057510-1049-COT26",
      "nombre": "compra materiales construcción para habilitación de áreas administrativas",
      "organismo": "SERVICIO DE SALUD NUBLE HOSPITAL DE SAN CARLOS DR BENICIO ARZOLA MEDIN",
      "region": "Región del Ñuble",
      "monto": 941028,
      "fecha_cierre": "2026-06-24 12:00",
      "estado": "Publicada",
      "url": "https://www.mercadopublico.cl/BuscarLicitacion?txtBuscar=1057510-1049-COT26",
      "url_directa": "https://www.mercadopublico.cl/Procurement/Modules/RFB/DetailsAcquisition.aspx?qs=1057510-1049-COT26"
    },
    {
      "codigo": "3249-78-COT26",
      "nombre": "ADQUISICIÓN DE MATERIALES PARA MANTENCION BASE AERONAVAL CONCON",
      "organismo": "BASE AERONAVAL CONCON",
      "region": "Región de Valparaíso ",
      "monto": 400000,
      "fecha_cierre": "2026-06-25 14:00",
      "estado": "Publicada",
      "url": "https://www.mercadopublico.cl/BuscarLicitacion?txtBuscar=3249-78-COT26",
      "url_directa": "https://www.mercadopublico.cl/Procurement/Modules/RFB/DetailsAcquisition.aspx?qs=3249-78-COT26"
    },
    {
      "codigo": "1111432-263-COT26",
      "nombre": "REEMPLAZO TECNICO EN PARVULO MEMO 119",
      "organismo": "CONSULTORIO GENERAL URBANO SAN FELIPE",
      "region": "Región de Valparaíso ",
      "monto": 540056,
      "fecha_cierre": "2026-06-24 12:00",
      "estado": "Publicada",
      "url": "https://www.mercadopublico.cl/BuscarLicitacion?txtBuscar=1111432-263-COT26",
      "url_directa": "https://www.mercadopublico.cl/Procurement/Modules/RFB/DetailsAcquisition.aspx?qs=1111432-263-COT26"
    },
    {
      "codigo": "1375761-177-COT26",
      "nombre": "Insumos de reparación para jardines VTF SLEP VALLE DIGUILLIN",
      "organismo": "SERVICIO LOCAL DE EDUCACIÓN PÚBLICA VALLE DIGUILLÍN",
      "region": "Región del Ñuble",
      "monto": 340000,
      "fecha_cierre": "2026-06-24 12:00",
      "estado": "Publicada",
      "url": "https://www.mercadopublico.cl/BuscarLicitacion?txtBuscar=1375761-177-COT26",
      "url_directa": "https://www.mercadopublico.cl/Procurement/Modules/RFB/DetailsAcquisition.aspx?qs=1375761-177-COT26"
    },
    {
      "codigo": "1079505-215-COT26",
      "nombre": "ADQUISICIÓN DE REPUESTOS PARA VEHÍCULOS FISCALES DE LA 3RA. COM. C.O.P. COQUIMBO",
      "organismo": "SECCIÓN COMPRAS IV ZONA",
      "region": "Región de Coquimbo ",
      "monto": 1000000,
      "fecha_cierre": "2026-06-24 13:00",
      "estado": "Publicada",
      "url": "https://www.mercadopublico.cl/BuscarLicitacion?txtBuscar=1079505-215-COT26",
      "url_directa": "https://www.mercadopublico.cl/Procurement/Modules/RFB/DetailsAcquisition.aspx?qs=1079505-215-COT26"
    },
    {
      "codigo": "3904-583-COT26",
      "nombre": "OP26-705 Adquisición de 3 Carros plataforma con barras laterales, para traslado de materiales de construcción y otros insumos pesados que llegan a la Dideco",
      "organismo": "I MUNICIPALIDAD DE BULNES",
      "region": "Región del Ñuble",
      "monto": 900000,
      "fecha_cierre": "2026-06-24 12:30",
      "estado": "Publicada",
      "url": "https://www.mercadopublico.cl/BuscarLicitacion?txtBuscar=3904-583-COT26",
      "url_directa": "https://www.mercadopublico.cl/Procurement/Modules/RFB/DetailsAcquisition.aspx?qs=3904-583-COT26"
    },
    {
      "codigo": "1288819-30-COT26",
      "nombre": "Arriendo, instalación y mantención de Lockers",
      "organismo": "SERVICIO NACIONAL DE PATRIMONIO",
      "region": "Región de la Araucanía ",
      "monto": 1200000,
      "fecha_cierre": "2026-06-26 15:00",
      "estado": "Publicada",
      "url": "https://www.mercadopublico.cl/BuscarLicitacion?txtBuscar=1288819-30-COT26",
      "url_directa": "https://www.mercadopublico.cl/Procurement/Modules/RFB/DetailsAcquisition.aspx?qs=1288819-30-COT26"
    },
    {
      "codigo": "3517-94-COT26",
      "nombre": "Mantención y reparación Camioneta JMC Departamento de Salud Municipal",
      "organismo": "I MUNICIPALIDAD DE TRAIGUEN",
      "region": "Región de la Araucanía ",
      "monto": 800000,
      "fecha_cierre": "2026-06-24 12:00",
      "estado": "Publicada",
      "url": "https://www.mercadopublico.cl/BuscarLicitacion?txtBuscar=3517-94-COT26",
      "url_directa": "https://www.mercadopublico.cl/Procurement/Modules/RFB/DetailsAcquisition.aspx?qs=3517-94-COT26"
    },
    {
      "codigo": "4850-25-COT26",
      "nombre": "Materiales para mantención",
      "organismo": "SERVICIO NACIONAL DEL PATRIMONIO CULTURAL",
      "region": "Región de Coquimbo ",
      "monto": 900000,
      "fecha_cierre": "2026-06-25 11:00",
      "estado": "Publicada",
      "url": "https://www.mercadopublico.cl/BuscarLicitacion?txtBuscar=4850-25-COT26",
      "url_directa": "https://www.mercadopublico.cl/Procurement/Modules/RFB/DetailsAcquisition.aspx?qs=4850-25-COT26"
    },
    {
      "codigo": "3436-224-COT26",
      "nombre": "Servicio limpieza alcantarillado batallón de los servicios Item 22.08.001 / SIC 347994",
      "organismo": "Ejercito de Chile",
      "region": "Región Metropolitana de Santiago",
      "monto": 3255840,
      "fecha_cierre": "2026-06-24 15:00",
      "estado": "Publicada",
      "url": "https://www.mercadopublico.cl/BuscarLicitacion?txtBuscar=3436-224-COT26",
      "url_directa": "https://www.mercadopublico.cl/Procurement/Modules/RFB/DetailsAcquisition.aspx?qs=3436-224-COT26"
    },
    {
      "codigo": "1402-197-COT26",
      "nombre": "ADQUISICIÓN DE SERVICIO DE REPARACION Y MANTENCION DE REFRIGERADOR DE CENTRAL DE ALIMENTACION DEL CCP DE RENGO",
      "organismo": "Dirección Regional de Gendarmeria - Rancagua",
      "region": "Región del Libertador General Bernardo O´Higgins",
      "monto": 276122,
      "fecha_cierre": "2026-06-24 12:00",
      "estado": "Publicada",
      "url": "https://www.mercadopublico.cl/BuscarLicitacion?txtBuscar=1402-197-COT26",
      "url_directa": "https://www.mercadopublico.cl/Procurement/Modules/RFB/DetailsAcquisition.aspx?qs=1402-197-COT26"
    },
    {
      "codigo": "885-528-COT26",
      "nombre": "Servicios de Mantención Preventiva del Grupo Electrógeno de la Sede Regional de Valparaíso, de acuerdo a los Términos de Referencia adjuntos",
      "organismo": "CONTRALORIA GENERAL DE LA REPUBLICA",
      "region": "Región de Valparaíso ",
      "monto": 2600000,
      "fecha_cierre": "2026-06-26 09:00",
      "estado": "Publicada",
      "url": "https://www.mercadopublico.cl/BuscarLicitacion?txtBuscar=885-528-COT26",
      "url_directa": "https://www.mercadopublico.cl/Procurement/Modules/RFB/DetailsAcquisition.aspx?qs=885-528-COT26"
    },
    {
      "codigo": "696750-28-COT26",
      "nombre": "CONTRATACIÓN DE SERVICIO DE CAFETERIA. FISCALÍAS LOCALES REGION DE LOS RÍOS",
      "organismo": "MINISTERIO PUBLICO",
      "region": "Región de Los Ríos",
      "monto": 848000,
      "fecha_cierre": "2026-06-25 09:00",
      "estado": "Publicada",
      "url": "https://www.mercadopublico.cl/BuscarLicitacion?txtBuscar=696750-28-COT26",
      "url_directa": "https://www.mercadopublico.cl/Procurement/Modules/RFB/DetailsAcquisition.aspx?qs=696750-28-COT26"
    },
    {
      "codigo": "1111432-262-COT26",
      "nombre": "REEMPLAZO TECNICO EN PARVULO MEMO 120",
      "organismo": "CONSULTORIO GENERAL URBANO SAN FELIPE",
      "region": "Región de Valparaíso ",
      "monto": 540056,
      "fecha_cierre": "2026-06-24 12:00",
      "estado": "Publicada",
      "url": "https://www.mercadopublico.cl/BuscarLicitacion?txtBuscar=1111432-262-COT26",
      "url_directa": "https://www.mercadopublico.cl/Procurement/Modules/RFB/DetailsAcquisition.aspx?qs=1111432-262-COT26"
    },
    {
      "codigo": "657-54-COT26",
      "nombre": "SERVICO DE EXAMEN INICIAL DE CONTROL DE CONSUMO DE SUSTANCIAS O DROGAS ESTUPEFACIENTES O PSICOTRÓPICAS ILEGALES",
      "organismo": "SERVICIO DE VIVIENDA Y URBANIZACION XI REGION",
      "region": "Región Aysén del General Carlos Ibáñez del Campo",
      "monto": 800000,
      "fecha_cierre": "2026-06-24 13:00",
      "estado": "Publicada",
      "url": "https://www.mercadopublico.cl/BuscarLicitacion?txtBuscar=657-54-COT26",
      "url_directa": "https://www.mercadopublico.cl/Procurement/Modules/RFB/DetailsAcquisition.aspx?qs=657-54-COT26"
    },
    {
      "codigo": "2711-151-COT26",
      "nombre": "Reparación minibus",
      "organismo": "MUNICIPALIDAD DE OVALLE",
      "region": "Región de Coquimbo ",
      "monto": 400000,
      "fecha_cierre": "2026-06-25 08:00",
      "estado": "Publicada",
      "url": "https://www.mercadopublico.cl/BuscarLicitacion?txtBuscar=2711-151-COT26",
      "url_directa": "https://www.mercadopublico.cl/Procurement/Modules/RFB/DetailsAcquisition.aspx?qs=2711-151-COT26"
    },
    {
      "codigo": "1340-41-COT26",
      "nombre": "ADQUISICIÓN DE Papel Plotter Bond 0.914x50mts. PAP-PB9150",
      "organismo": "MINISTERIO DE OBRAS PUBLICAS DIREC CION GRAL DE OO PP DCYF",
      "region": "Región de Los Ríos",
      "monto": 300000,
      "fecha_cierre": "2026-06-29 12:00",
      "estado": "Publicada",
      "url": "https://www.mercadopublico.cl/BuscarLicitacion?txtBuscar=1340-41-COT26",
      "url_directa": "https://www.mercadopublico.cl/Procurement/Modules/RFB/DetailsAcquisition.aspx?qs=1340-41-COT26"
    },
    {
      "codigo": "4195-579-COT26",
      "nombre": "SERVICIO ARRIENDO DE EXCAVADORA PARA MANTENCION DE CAMINOS EN ISLA CAUCAHUE",
      "organismo": "I MUNICIPALIDAD DE QUEMCHI",
      "region": "Región de los Lagos ",
      "monto": 1500000,
      "fecha_cierre": "2026-06-24 12:00",
      "estado": "Publicada",
      "url": "https://www.mercadopublico.cl/BuscarLicitacion?txtBuscar=4195-579-COT26",
      "url_directa": "https://www.mercadopublico.cl/Procurement/Modules/RFB/DetailsAcquisition.aspx?qs=4195-579-COT26"
    },
    {
      "codigo": "1407-107-COT26",
      "nombre": "CRS IQQ COMPRA ÚTILES DE ASEO PARA LIMPIEZA DE VEHICULO FISCAL ",
      "organismo": "Dirección Regional de Gendarmeria - Iquique",
      "region": "Región de Tarapacá  ",
      "monto": 695960,
      "fecha_cierre": "2026-06-25 10:30",
      "estado": "Publicada",
      "url": "https://www.mercadopublico.cl/BuscarLicitacion?txtBuscar=1407-107-COT26",
      "url_directa": "https://www.mercadopublico.cl/Procurement/Modules/RFB/DetailsAcquisition.aspx?qs=1407-107-COT26"
    },
    {
      "codigo": "831-118-COT26",
      "nombre": "Adquisición de chalecos tipo Geólogos para el Departamento Control de Obras.",
      "organismo": "GOBIERNO REGIONAL DE LA REGION DEL BIO BIO",
      "region": "Región del Biobío ",
      "monto": 315000,
      "fecha_cierre": "2026-06-24 19:00",
      "estado": "Publicada",
      "url": "https://www.mercadopublico.cl/BuscarLicitacion?txtBuscar=831-118-COT26",
      "url_directa": "https://www.mercadopublico.cl/Procurement/Modules/RFB/DetailsAcquisition.aspx?qs=831-118-COT26"
    },
    {
      "codigo": "872535-241-COT26",
      "nombre": "Adquisición de servicio de mantención de plotter",
      "organismo": "I MUNICIPALIDAD DE TENO",
      "region": "Región del Maule ",
      "monto": 980000,
      "fecha_cierre": "2026-06-26 08:00",
      "estado": "Publicada",
      "url": "https://www.mercadopublico.cl/BuscarLicitacion?txtBuscar=872535-241-COT26",
      "url_directa": "https://www.mercadopublico.cl/Procurement/Modules/RFB/DetailsAcquisition.aspx?qs=872535-241-COT26"
    },
    {
      "codigo": "1729-247-COT26",
      "nombre": "Servicio de Consultoria",
      "organismo": "I MUNICIPALIDAD DE TIERRA AMARILLA",
      "region": "Región de Atacama ",
      "monto": 6500000,
      "fecha_cierre": "2026-06-24 12:00",
      "estado": "Publicada",
      "url": "https://www.mercadopublico.cl/BuscarLicitacion?txtBuscar=1729-247-COT26",
      "url_directa": "https://www.mercadopublico.cl/Procurement/Modules/RFB/DetailsAcquisition.aspx?qs=1729-247-COT26"
    },
    {
      "codigo": "1729-248-COT26",
      "nombre": "MANTENCION DE VEHICULOS MUNICIPALES",
      "organismo": "I MUNICIPALIDAD DE TIERRA AMARILLA",
      "region": "Región de Atacama ",
      "monto": 3342000,
      "fecha_cierre": "2026-06-24 11:45",
      "estado": "Publicada",
      "url": "https://www.mercadopublico.cl/BuscarLicitacion?txtBuscar=1729-248-COT26",
      "url_directa": "https://www.mercadopublico.cl/Procurement/Modules/RFB/DetailsAcquisition.aspx?qs=1729-248-COT26"
    },
    {
      "codigo": "3220-315-COT26",
      "nombre": " ESTADO DE EXCEPCION CONSTITUCIONAL MZS / MANTENCIÓN Y RECARGA DE EXTINTORES",
      "organismo": "COMANDANCIA EN JEFE DE LA IIa. ZONA NAVAL",
      "region": "Región del Biobío ",
      "monto": 450000,
      "fecha_cierre": "2026-06-24 11:45",
      "estado": "Publicada",
      "url": "https://www.mercadopublico.cl/BuscarLicitacion?txtBuscar=3220-315-COT26",
      "url_directa": "https://www.mercadopublico.cl/Procurement/Modules/RFB/DetailsAcquisition.aspx?qs=3220-315-COT26"
    },
    {
      "codigo": "1079967-440-COT26",
      "nombre": "SERVICIO DE MANTENIMIENTO Y REPARACIÓN PARA EL VEHÍCULO POLICIAL AP-3089 DE CARGO DE LA PREFECTURA IQUIQUE.",
      "organismo": "SECCIÓN COMPRAS I ZONA",
      "region": "Región de Tarapacá  ",
      "monto": 892500,
      "fecha_cierre": "2026-06-24 12:00",
      "estado": "Publicada",
      "url": "https://www.mercadopublico.cl/BuscarLicitacion?txtBuscar=1079967-440-COT26",
      "url_directa": "https://www.mercadopublico.cl/Procurement/Modules/RFB/DetailsAcquisition.aspx?qs=1079967-440-COT26"
    },
    {
      "codigo": "1430396-70-COT26",
      "nombre": "Mantención, Instalación y Reparación de equipos de Aire Acondicionado",
      "organismo": "CORPORACIÓN CULTURAL DE ÑUÑOA",
      "region": "Región Metropolitana de Santiago",
      "monto": 7000000,
      "fecha_cierre": "2026-06-29 16:00",
      "estado": "Publicada",
      "url": "https://www.mercadopublico.cl/BuscarLicitacion?txtBuscar=1430396-70-COT26",
      "url_directa": "https://www.mercadopublico.cl/Procurement/Modules/RFB/DetailsAcquisition.aspx?qs=1430396-70-COT26"
    },
    {
      "codigo": "1079454-412-COT26",
      "nombre": "ADQUISICIÓN DE REPUESTOS DESTINADOS AL VEHÍCULO FISCAL (AP-3060) A CARGO DEL RETÉN INACALIRI (F) SEGÚN N.C.U.:254290143.",
      "organismo": "SECCIÓN COMPRAS II ZONA",
      "region": "Región de Antofagasta ",
      "monto": 210000,
      "fecha_cierre": "2026-06-25 10:30",
      "estado": "Publicada",
      "url": "https://www.mercadopublico.cl/BuscarLicitacion?txtBuscar=1079454-412-COT26",
      "url_directa": "https://www.mercadopublico.cl/Procurement/Modules/RFB/DetailsAcquisition.aspx?qs=1079454-412-COT26"
    },
    {
      "codigo": "3019-351-COT26",
      "nombre": "Reparación y mantención puertas automáticas de los Centros de Salud - Solicitud de compra N°47",
      "organismo": "I.MUNICIPALIDAD DE LOTA - SALUD",
      "region": "Región del Biobío ",
      "monto": 1200000,
      "fecha_cierre": "2026-06-24 12:00",
      "estado": "Publicada",
      "url": "https://www.mercadopublico.cl/BuscarLicitacion?txtBuscar=3019-351-COT26",
      "url_directa": "https://www.mercadopublico.cl/Procurement/Modules/RFB/DetailsAcquisition.aspx?qs=3019-351-COT26"
    },
    {
      "codigo": "3416-149-COT26",
      "nombre": "LIMPIEZA DE ALCANTARILLADO Y CAMARAS DESGRASADORAS",
      "organismo": "Ejercito de Chile",
      "region": "Región Metropolitana de Santiago",
      "monto": 1942200,
      "fecha_cierre": "2026-06-24 11:40",
      "estado": "Publicada",
      "url": "https://www.mercadopublico.cl/BuscarLicitacion?txtBuscar=3416-149-COT26",
      "url_directa": "https://www.mercadopublico.cl/Procurement/Modules/RFB/DetailsAcquisition.aspx?qs=3416-149-COT26"
    },
    {
      "codigo": "5586-1542-COT26",
      "nombre": "B/S Mantención equipo HPLC ",
      "organismo": "UNIVERSIDAD DE LA FRONTERA",
      "region": "Región de la Araucanía ",
      "monto": 2620000,
      "fecha_cierre": "2026-06-24 15:00",
      "estado": "Publicada",
      "url": "https://www.mercadopublico.cl/BuscarLicitacion?txtBuscar=5586-1542-COT26",
      "url_directa": "https://www.mercadopublico.cl/Procurement/Modules/RFB/DetailsAcquisition.aspx?qs=5586-1542-COT26"
    },
    {
      "codigo": "2176-179-COT26",
      "nombre": "Mantencion camioneta Nissan Terrano 2014",
      "organismo": "CORP ADMINISTRATIVA DEL PODER JUDICIAL",
      "region": "Región de Valparaíso ",
      "monto": 500000,
      "fecha_cierre": "2026-06-25 15:00",
      "estado": "Publicada",
      "url": "https://www.mercadopublico.cl/BuscarLicitacion?txtBuscar=2176-179-COT26",
      "url_directa": "https://www.mercadopublico.cl/Procurement/Modules/RFB/DetailsAcquisition.aspx?qs=2176-179-COT26"
    },
    {
      "codigo": "3561-279-COT26",
      "nombre": "FLUXOMETROS PARA REPARACIÓN BAÑOS",
      "organismo": "I MUNICIPALIDAD DE LA CALERA",
      "region": "Región de Valparaíso ",
      "monto": 920000,
      "fecha_cierre": "2026-06-24 11:30",
      "estado": "Publicada",
      "url": "https://www.mercadopublico.cl/BuscarLicitacion?txtBuscar=3561-279-COT26",
      "url_directa": "https://www.mercadopublico.cl/Procurement/Modules/RFB/DetailsAcquisition.aspx?qs=3561-279-COT26"
    },
    {
      "codigo": "1016414-29-COT26",
      "nombre": "Carpinterías de tabiquerías y terminaciones de revestimientos en placas de yeso cartón y pavimentos de piso flotantes",
      "organismo": "CONSEJO NACIONAL DE TELEVISION",
      "region": "Región Metropolitana de Santiago",
      "monto": 3400000,
      "fecha_cierre": "2026-06-26 14:00",
      "estado": "Publicada",
      "url": "https://www.mercadopublico.cl/BuscarLicitacion?txtBuscar=1016414-29-COT26",
      "url_directa": "https://www.mercadopublico.cl/Procurement/Modules/RFB/DetailsAcquisition.aspx?qs=1016414-29-COT26"
    }
  ],
  "licitaciones": [],
  "total_compras": 6926,
  "total_licitaciones": 0,
  "error_lic": "no such table: licitaciones"
}